pdfoutline/__init__.py
pdfoutline/main.py
pdfoutline/pdfoutline.py
pdfoutline-0.0.0.dist-info/LICENSE
pdfoutline-0.0.0.dist-info/METADATA
pdfoutline-0.0.0.dist-info/WHEEL
pdfoutline-0.0.0.dist-info/entry_points.txt
pdfoutline-0.0.0.dist-info/top_level.txt
pdfoutline-0.0.0.dist-info/RECORD
