Metadata-Version: 2.1
Name: pdfoutline
Version: 0.0.0
Summary: A command line tool for adding an outline to pdf files
Home-page: https://github.com/eggplants/getjump
Author: Yuta Yamamoto
Author-email: jichael.y.yuta1995@gmail.com
License: MIT
Platform: UNKNOWN
Classifier: License :: OSI Approved :: MIT License
Classifier: Programming Language :: Python
Classifier: Programming Language :: Python :: 3
Classifier: Programming Language :: Python :: 3 :: Only
Classifier: Programming Language :: Python :: 3.7
Classifier: Programming Language :: Python :: 3.8
Classifier: Programming Language :: Python :: 3.9
Classifier: Programming Language :: Python :: 3.10
Classifier: Programming Language :: Python :: Implementation :: CPython
Requires-Python: >=3.7
License-File: LICENSE
Provides-Extra: dev
Requires-Dist: per-commit ; extra == 'dev'
Requires-Dist: setuptools (>=46.4.0) ; extra == 'dev'
